birdhousebuilder.recipe.conda-0.3.6-py2.7-nspkg.pth
birdhousebuilder/recipe/conda/README.txt
birdhousebuilder/recipe/conda/__init__.py
birdhousebuilder/recipe/conda/tests/__init__.py
birdhousebuilder/recipe/conda/tests/test_docs.py
birdhousebuilder/recipe/conda/tests/test_doctests.py
birdhousebuilder.recipe.conda-0.3.6.dist-info/DESCRIPTION.rst
birdhousebuilder.recipe.conda-0.3.6.dist-info/METADATA
birdhousebuilder.recipe.conda-0.3.6.dist-info/RECORD
birdhousebuilder.recipe.conda-0.3.6.dist-info/WHEEL
birdhousebuilder.recipe.conda-0.3.6.dist-info/entry_points.txt
birdhousebuilder.recipe.conda-0.3.6.dist-info/metadata.json
birdhousebuilder.recipe.conda-0.3.6.dist-info/namespace_packages.txt
birdhousebuilder.recipe.conda-0.3.6.dist-info/pbr.json
birdhousebuilder.recipe.conda-0.3.6.dist-info/top_level.txt
