Metadata-Version: 2.0
Name: birdhousebuilder.recipe.conda
Version: 0.3.6
Summary: A Buildout recipe to install conda packages
Home-page: https://github.com/bird-house/birdhousebuilder.recipe.conda
Author: Birdhouse
Author-email: wps-dev at dkrz.de
License: Apache License 2
Keywords: buildout recipe conda anaconda birdhouse
Platform: UNKNOWN
Classifier: Framework :: Buildout
Classifier: Intended Audience :: Developers
Classifier: Topic :: Software Development :: Build Tools
Classifier: Topic :: Software Development :: Libraries :: Python Modules
Classifier: License :: OSI Approved :: BSD License
Requires-Dist: pyyaml
Requires-Dist: setuptools
Requires-Dist: zc.buildout
Provides-Extra: tests
Requires-Dist: zc.buildout; extra == 'tests'
Requires-Dist: zope.testing; extra == 'tests'
